amazon_ss1/__init__.py
amazon_ss1/add_one.py
amazon_ss1/ap_region.py
amazon_ss1/version.py
amazon_ss1-2.7.1.dist-info/LICENSE.txt
amazon_ss1-2.7.1.dist-info/METADATA
amazon_ss1-2.7.1.dist-info/NOTICE.txt
amazon_ss1-2.7.1.dist-info/WHEEL
amazon_ss1-2.7.1.dist-info/top_level.txt
amazon_ss1-2.7.1.dist-info/RECORD
