Metadata-Version: 2.1
Name: amazon-ss1
Version: 2.7.1
Summary: Amazon ss Python SDK
Author: EPS-DSE
Author-email: amazon-pay-sdk@amazon.com
License: Apache License version 2.0, January 2004
Keywords: Amazon,Payments,Login,Python,API,SDK
Classifier: Development Status :: 5 - Production/Stable
Classifier: Intended Audience :: Developers
Classifier: License :: OSI Approved :: Apache Software License
Classifier: Natural Language :: English
Classifier: Operating System :: OS Independent
Classifier: Programming Language :: Python
Classifier: Programming Language :: Python :: 3.2
Classifier: Programming Language :: Python :: 3.4
Classifier: Topic :: Software Development :: Libraries
Classifier: Topic :: Software Development :: Libraries :: Python Modules
License-File: LICENSE.txt
License-File: NOTICE.txt
Requires-Dist: pyOpenSSL (>=0.11)
Requires-Dist: requests (>=2.6.0)
